{
  ".NET Developer": "NEUTRAL",
  "AI Engineer": "GOOD_FIT",
  "AI Research Engineer": "NEUTRAL",
  "AI Specialist": "NEUTRAL",
  "Accountant": "BAD_FIT",
  "Analytics Engineer": "NEUTRAL",
  "Applied ML Engineer": "GOOD_FIT",
  "Backend Engineer": "NEUTRAL",
  "Business Analyst": "BAD_FIT",
  "Civil Engineer": "BAD_FIT",
  "Cloud Engineer": "NEUTRAL",
  "Computer Vision Engineer": "NEUTRAL",
  "Content Writer": "BAD_FIT",
  "Customer Support": "BAD_FIT",
  "Data Analyst": "BAD_FIT",
  "Data Engineer": "NEUTRAL",
  "Data Scientist": "NEUTRAL",
  "DevOps Engineer": "NEUTRAL",
  "Frontend Engineer": "NEUTRAL",
  "Full Stack Developer": "NEUTRAL",
  "Graphic Designer": "BAD_FIT",
  "HR Manager": "BAD_FIT",
  "Java Developer": "NEUTRAL",
  "Junior ML Engineer": "NEUTRAL",
  "Lead AI Engineer": "GOOD_FIT",
  "ML Engineer": "GOOD_FIT",
  "Machine Learning Engineer": "GOOD_FIT",
  "Marketing Manager": "BAD_FIT",
  "Mechanical Engineer": "BAD_FIT",
  "Mobile Developer": "NEUTRAL",
  "NLP Engineer": "GOOD_FIT",
  "Operations Manager": "BAD_FIT",
  "Project Manager": "BAD_FIT",
  "QA Engineer": "BAD_FIT",
  "Recommendation Systems Engineer": "GOOD_FIT",
  "Sales Executive": "BAD_FIT",
  "Search Engineer": "GOOD_FIT",
  "Senior AI Engineer": "GOOD_FIT",
  "Senior Applied Scientist": "GOOD_FIT",
  "Senior Data Engineer": "NEUTRAL",
  "Senior Data Scientist": "NEUTRAL",
  "Senior ML Engineer — Search & Ranking": "GOOD_FIT",
  "Senior Machine Learning Engineer": "GOOD_FIT",
  "Senior NLP Engineer": "GOOD_FIT",
  "Senior Software Engineer": "NEUTRAL",
  "Senior Software Engineer (ML)": "GOOD_FIT",
  "Software Engineer": "NEUTRAL",
  "Staff Machine Learning Engineer": "GOOD_FIT"
}
